{
    "entries": {
        "@tip_default": "Try again later. If the problem persists, please contact Player Support.",
        "@tip_type_login_error": "Login error. Please try again later.",
        "@tip_type_logout_error": "Logout error.",
        "@tip_type_profile_sync_error": "Failed to synchronize profile from the server.",
        "@tip_type_inventory_sync_error": "Failed to synchronize inventory from the server.",
        "@tip_type_inventory_validation_error": "Inventory service is temporarily unavailable.",
        "@tip_type_quickplay_service_unavaiable": "Quickplay service is temporarily unavailable.",
        "@tip_type_quickplay_service_timeout": "No match found. Please try again or change game mode.",
        "@tip_type_purchase_error": "Failed to complete purchase request. Please try again later.",
        "@tip_type_server_connection_error": "Failed to connect to the server.",
        "@tip_type_task_service_unavaiable": "Tasks service is temporarily unavailable.",
        "@tip_type_friend_service_unavaiable": "Friends service is temporarily unavailable.",
        "@tip_type_party_service_unavaiable": "Party service is temporarily unavailable.",
        "@tip_type_party_request_failed": "Request failed. Please try again.",
        "@tip_type_notification_service_unavaiable": "Notifications service is temporarily unavailable.",
        "@tip_type_support_system_error": "Support system error.",
        "@tip_type_eos_sanction_applied": "Sanction applied.",
        "@tip_detail_update_client": "Your game requires an update.",
        "@tip_detail_not_enough_money": "Sorry, you don't have enough funds.",
        "@tip_detail_eac_integrity_violation": "Please repair your installation.",
        "@tip_detail_closed_for_maintenance": "Sorry, the servers are down for maintenance.",
        "@tip_detail_user_banned": "You have been banned.",
        "@tip_detail_concurrent_login": "Concurrent login detected.",
        "@tip_detail_exceeded_online_players_limit": "Sorry, the servers are overloaded.",
        "@tip_detail_eac_failed_to_init": "Anticheat system failed to initialize. Please try to repair it.",
        "@tip_detail_access_violation": "Unauthorized access.",
        "@tip_detail_server_lost_connection": "Connection with game server lost.",
        "@tip_detail_server_connection_failed": "Connection to game server failed.",
        "@tip_detail_ds_allocation_failed": "No available servers left, please try again later.",
        "@tip_detail_matchmaking_failed": "Matchmaking failed, please try again later.",
        "@tip_detail_territories_not_specified": "Incorrect server region. Please change the region in the Lobby.",
        "@tip_detail_party_is_full": "Party is already full.",
        "@tip_detail_party_invite_not_found": "Party invite not found.",
        "@tip_detail_not_party_leader": "You are not the party leader.",
        "@tip_detail_already_in_party": "You are already in the party.",
        "@tip_detail_craft_reward_invalid": "Sorry, invalid reward received. Please contact Player Support.",
        "@tip_detail_timeout_error": "Request timeout exceeded.",
        "@tip_detail_clan_loading_error": "Failed to load clan status.",
        "@tip_inventory_item_not_found": "Inventory item not found.",
        "@tip_no_active_season": "No active season.",
        "@tip_season_paid_track_already_unlocked": "Premium Season track is already unlocked.",
        "@tip_invalid_email": "Invalid email.",
        "@tip_support_unavailable": "Support service is temporarily unavailable. Please try again later.",
        "@tip_ticket_not_created": "Error while creating support ticket. Please try again later.",
        "@tip_need_to_enable_steam_overlay": "Please enable the in-game Steam overlay in your Steam settings to proceed.",
        "@tip_secure_connection_failed": "Secure connection failed.",
        "@tip_login_queue_full": "Login queue is full. Please try again in a few minutes.",
        "@tip_failed_to_connect_eos": "EOS failed to connect.",
        "@tip_eos_restricted_game_access": "Access to the game was restricted.",
        "@tip_eos_cannot_load_sanctions": "Error while loading sanctions list. Please try again.",
        "@tip_eos_restricted_mm": "Access to matchmaking was restricted.",
        "@tip_steam_init_failed": "Please relaunch the game through Steam.",
        "@tip_steam_token_error": "Please make sure Steam is in Online mode. Please try again.",
        "@tip_websocket_connection_lost": "Websocket connection lost.",
        "@tip_creator_not_found": "Creator ID not found.",
        "@tip_redeem_coupon_not_found": "Redeem code not found.",
        "@tip_sync_entitlements_failed": "We failed to sync your purchase. We will try again with your next purchase or next login.",
        "@tip_authentication_forbidden_no_privilege": "The servers are closed for maintenance.",
        "@tip_egs_token_error": "Please make sure Epic Games Launcher is in Online mode. Try again.",
        "@tip_not_enough_consumed_items": "Not enough consumable items to continue operation.",
        "@tip_eos_jwt_verification_error": "EOS Identity Provider not responding. Please contact live support.",
        "@tip_detail_qos_limit_reached": "Oops, we are trying to send too many requests. Please report this issue."
    }
}